dzero_python/__init__.py
dzero_python/constants.py
dzero_python/simple_test.py
dzero_python/segments/__init__.py
dzero_python/segments/additional_documentation.py
dzero_python/segments/base.py
dzero_python/segments/claim.py
dzero_python/segments/clinical.py
dzero_python/segments/compound.py
dzero_python/segments/coord_of_benefits.py
dzero_python/segments/coupon.py
dzero_python/segments/dur_pps.py
dzero_python/segments/facility.py
dzero_python/segments/insurance.py
dzero_python/segments/narrative.py
dzero_python/segments/patient.py
dzero_python/segments/pharmacy_provider.py
dzero_python/segments/prescriber.py
dzero_python/segments/pricing.py
dzero_python/segments/prior_auth.py
dzero_python/segments/response_claim.py
dzero_python/segments/response_coord_of_benefits.py
dzero_python/segments/response_dur_pps.py
dzero_python/segments/response_insurance.py
dzero_python/segments/response_insurance_additional_documentation.py
dzero_python/segments/response_message.py
dzero_python/segments/response_patient.py
dzero_python/segments/response_pricing.py
dzero_python/segments/response_prior_auth.py
dzero_python/segments/response_status.py
dzero_python/segments/workers_comp.py
dzero_python/segments/concerns/__init__.py
dzero_python/segments/concerns/parser.py
dzero_python/segments/concerns/serializer.py
dzero_python/transmissions/__init__.py
dzero_python/transmissions/base.py
dzero_python/transmissions/request.py
dzero_python/transmissions/response.py
dzero_python/transmissions/concerns/__init__.py
dzero_python/transmissions/concerns/parser.py
dzero_python/transmissions/concerns/segments_methods.py
dzero_python/transmissions/concerns/serializer.py
dzero_python/transmissions/groups/__init__.py
dzero_python/transmissions/groups/base.py
dzero_python/transmissions/groups/transaction_group.py
dzero_python/transmissions/groups/transmission_group.py
dzero_python/utils/__init__.py
dzero_python/utils/fixed_width.py
dzero_python/utils/rejection_codes.py
dzero_python/utils/validator.py
dzero_python-1.0.2.dist-info/METADATA
dzero_python-1.0.2.dist-info/WHEEL
dzero_python-1.0.2.dist-info/top_level.txt
dzero_python-1.0.2.dist-info/RECORD
